markitdown/__about__.py
markitdown/__init__.py
markitdown/__main__.py
markitdown/_base_converter.py
markitdown/_exceptions.py
markitdown/_markitdown.py
markitdown/_stream_info.py
markitdown/_uri_utils.py
markitdown/py.typed
markitdown/converter_utils/__init__.py
markitdown/converter_utils/docx/__init__.py
markitdown/converter_utils/docx/pre_process.py
markitdown/converter_utils/docx/math/__init__.py
markitdown/converter_utils/docx/math/latex_dict.py
markitdown/converter_utils/docx/math/omml.py
markitdown/converters/__init__.py
markitdown/converters/_audio_converter.py
markitdown/converters/_bing_serp_converter.py
markitdown/converters/_csv_converter.py
markitdown/converters/_doc_intel_converter.py
markitdown/converters/_docx_converter.py
markitdown/converters/_epub_converter.py
markitdown/converters/_exiftool.py
markitdown/converters/_html_converter.py
markitdown/converters/_image_converter.py
markitdown/converters/_ipynb_converter.py
markitdown/converters/_llm_caption.py
markitdown/converters/_markdownify.py
markitdown/converters/_outlook_msg_converter.py
markitdown/converters/_pdf_converter.py
markitdown/converters/_plain_text_converter.py
markitdown/converters/_pptx_converter.py
markitdown/converters/_rss_converter.py
markitdown/converters/_transcribe_audio.py
markitdown/converters/_wikipedia_converter.py
markitdown/converters/_xlsx_converter.py
markitdown/converters/_youtube_converter.py
markitdown/converters/_zip_converter.py
markitdown_pdf_separators-0.4.3.dist-info/METADATA
markitdown_pdf_separators-0.4.3.dist-info/WHEEL
markitdown_pdf_separators-0.4.3.dist-info/entry_points.txt
markitdown_pdf_separators-0.4.3.dist-info/RECORD
