Metadata-Version: 2.4
Name: markitdown-pdf-separators
Version: 0.4.3
Summary: MarkItDown with PDF page separators - convert PDFs to Markdown with page boundary markers
Project-URL: Documentation, https://github.com/Staceypy/markitdown-pdf-separators#readme
Project-URL: Issues, https://github.com/Staceypy/markitdown-pdf-separators/issues
Project-URL: Source, https://github.com/Staceypy/markitdown-pdf-separators
Project-URL: Repository, https://github.com/Staceypy/markitdown-pdf-separators
Author-email: Yu Pei <yu.pei00q@gmail.com>
License-Expression: MIT
Keywords: converter,document-conversion,markdown,page-separators,pdf
Classifier: Development Status :: 4 - Beta
Classifier: Programming Language :: Python
Classifier: Programming Language :: Python :: 3.10
Classifier: Programming Language :: Python :: 3.11
Classifier: Programming Language :: Python :: 3.12
Classifier: Programming Language :: Python :: 3.13
Classifier: Programming Language :: Python :: Implementation :: CPython
Classifier: Programming Language :: Python :: Implementation :: PyPy
Classifier: Topic :: Software Development :: Libraries :: Python Modules
Classifier: Topic :: Text Processing :: Markup
Requires-Python: >=3.10
Requires-Dist: beautifulsoup4
Requires-Dist: charset-normalizer
Requires-Dist: defusedxml
Requires-Dist: magika~=0.6.1
Requires-Dist: markdownify
Requires-Dist: onnxruntime<=1.20.1; sys_platform == 'win32'
Requires-Dist: requests
Provides-Extra: all
Requires-Dist: azure-ai-documentintelligence; extra == 'all'
Requires-Dist: azure-identity; extra == 'all'
Requires-Dist: lxml; extra == 'all'
Requires-Dist: mammoth; extra == 'all'
Requires-Dist: olefile; extra == 'all'
Requires-Dist: openpyxl; extra == 'all'
Requires-Dist: pandas; extra == 'all'
Requires-Dist: pdfminer-six; extra == 'all'
Requires-Dist: pydub; extra == 'all'
Requires-Dist: pymupdf; extra == 'all'
Requires-Dist: python-pptx; extra == 'all'
Requires-Dist: speechrecognition; extra == 'all'
Requires-Dist: xlrd; extra == 'all'
Requires-Dist: youtube-transcript-api~=1.0.0; extra == 'all'
Provides-Extra: audio-transcription
Requires-Dist: pydub; extra == 'audio-transcription'
Requires-Dist: speechrecognition; extra == 'audio-transcription'
Provides-Extra: az-doc-intel
Requires-Dist: azure-ai-documentintelligence; extra == 'az-doc-intel'
Requires-Dist: azure-identity; extra == 'az-doc-intel'
Provides-Extra: docx
Requires-Dist: lxml; extra == 'docx'
Requires-Dist: mammoth; extra == 'docx'
Provides-Extra: outlook
Requires-Dist: olefile; extra == 'outlook'
Provides-Extra: pdf
Requires-Dist: pdfminer-six; extra == 'pdf'
Provides-Extra: pdf-advanced
Requires-Dist: pdfminer-six; extra == 'pdf-advanced'
Requires-Dist: pymupdf; extra == 'pdf-advanced'
Provides-Extra: pptx
Requires-Dist: python-pptx; extra == 'pptx'
Provides-Extra: xls
Requires-Dist: pandas; extra == 'xls'
Requires-Dist: xlrd; extra == 'xls'
Provides-Extra: xlsx
Requires-Dist: openpyxl; extra == 'xlsx'
Requires-Dist: pandas; extra == 'xlsx'
Provides-Extra: youtube-transcription
Requires-Dist: youtube-transcript-api; extra == 'youtube-transcription'
